volpy/__init__.py
volpy/coordinates.py
volpy/geometry.py
volpy/plots.py
volpy/survey.py
volpy/utils.py
volpy/sample_data/survey_ibema_faxinal_Cartesian.csv
volpy-21.4.1.dist-info/LICENSE
volpy-21.4.1.dist-info/METADATA
volpy-21.4.1.dist-info/WHEEL
volpy-21.4.1.dist-info/top_level.txt
volpy-21.4.1.dist-info/RECORD
