Metadata-Version: 2.1
Name: volpy
Version: 21.4.1
Summary: volpy: Volume calculations in Python
Home-page: https://github.com/agu3rra/volpy/
Author: Andre Guerra
Author-email: agu3rra@me.com
License: MIT
Keywords: gps volume terrain survey
Platform: UNKNOWN
Requires-Dist: numpy (==1.20.0)
Requires-Dist: scipy (==1.3.1)
Requires-Dist: pandas (==1.2.4)
Requires-Dist: utm (==0.7.0)
Requires-Dist: sympy (==1.6.2)
Requires-Dist: plotly (==4.14.3)
Requires-Dist: defusedxml (==0.7.1)
